otel_ci/__init__.py
otel_ci/cli.py
otel_ci/exec.py
otel_ci/github.py
otel_ci/logging.py
otel_ci/replay.py
otel_ci/settings.py
otel_ci/trace.py
otel_ci-0.3.0.dist-info/METADATA
otel_ci-0.3.0.dist-info/WHEEL
otel_ci-0.3.0.dist-info/entry_points.txt
otel_ci-0.3.0.dist-info/RECORD
