Metadata-Version: 2.4
Name: otel-ci
Version: 0.3.0
Summary: Add your description here
Requires-Python: <3.14,>=3.12.1
Requires-Dist: opentelemetry-exporter-otlp==1.36.0
